jupyter_pgadmin_proxy/__init__.py
jupyter_pgadmin_proxy/pgadmin.svg
jupyter_pgadmin_proxy-0.0.4.dist-info/METADATA
jupyter_pgadmin_proxy-0.0.4.dist-info/WHEEL
jupyter_pgadmin_proxy-0.0.4.dist-info/entry_points.txt
jupyter_pgadmin_proxy-0.0.4.dist-info/licenses/LICENSE.md
jupyter_pgadmin_proxy-0.0.4.dist-info/RECORD
