Metadata-Version: 2.4
Name: jupyter-pgadmin-proxy
Version: 0.0.4
Summary: Jupyter server proxy for pgAdmin
Project-URL: Homepage, https://github.com/huntdatacenter/jupyter-pgadmin-proxy
Author-email: Matus Kosut <matus.kosut@ntnu.no>, Diepiriye Okujagu <diepiriye.d.okujagu@ntnu.no>
License: MIT License
License-File: LICENSE.md
Keywords: Jupyter Proxy,Jupyter Server Proxy,JupyterLab
Classifier: Framework :: Jupyter
Classifier: Framework :: Jupyter :: JupyterLab
Classifier: Intended Audience :: Developers
Classifier: License :: OSI Approved :: MIT License
Classifier: Natural Language :: English
Classifier: Programming Language :: Python :: 3
Classifier: Programming Language :: Python :: 3.8
Classifier: Programming Language :: Python :: 3.9
Classifier: Programming Language :: Python :: 3.10
Classifier: Programming Language :: Python :: 3.11
Classifier: Programming Language :: Python :: 3.12
Classifier: Programming Language :: Python :: 3.13
Requires-Python: >=3.8
Requires-Dist: gunicorn
Requires-Dist: jupyter-server-proxy
Requires-Dist: pgadmin4
Requires-Dist: psycopg
Requires-Dist: simple-websocket
Provides-Extra: dev
Requires-Dist: black; extra == 'dev'
Requires-Dist: pytest; extra == 'dev'
Requires-Dist: pytest-cov; extra == 'dev'
Requires-Dist: ruamel-yaml; extra == 'dev'
